imgfn/__main__.py
imgfn/colour.py
imgfn/lines.py
imgfn/mutation.py
imgfn/test.py
imgfn-1.0.0.dist-info/METADATA
imgfn-1.0.0.dist-info/WHEEL
imgfn-1.0.0.dist-info/top_level.txt
imgfn-1.0.0.dist-info/RECORD
