Metadata-Version: 2.1
Name: imgfn
Version: 1.0.0
Summary: Lots of random image functions
Home-page: https://github.com/judev1
Author: Jude BC
Author-email: jude.version1.0@gmail.com
License: BSD 2-clause
Platform: UNKNOWN
Classifier: Development Status :: 3 - Alpha
Classifier: Intended Audience :: Developers
Classifier: License :: OSI Approved :: GNU General Public License v3 (GPLv3)
Classifier: Operating System :: Microsoft
Classifier: Programming Language :: Python :: 2
Classifier: Programming Language :: Python :: 3
